tempsdb-0.6.5.dist-info/METADATA
tempsdb-0.6.5.dist-info/RECORD
tempsdb-0.6.5.dist-info/LICENSE
tempsdb-0.6.5.dist-info/zip-safe
tempsdb-0.6.5.dist-info/top_level.txt
tempsdb-0.6.5.dist-info/WHEEL
tempsdb/__init__.py
tempsdb/__bootstrap__.cpython-310-arm-linux-gnueabihf.so
tempsdb/chunks/__init__.py
