Metadata-Version: 2.1
Name: tempsdb
Version: 0.6.5
Summary: Embedded Cython database for time series that you need to send somewhere
Home-page: https://github.com/smok-serwis/tempsdb
Author: Piotr Maślanka
Author-email: pmaslanka@smok.co
Project-URL: Documentation, https://tempsdb.readthedocs.io/
Project-URL: Code, https://github.com/smok-serwis/tempsdb
Project-URL: Issue tracker, https://github.com/smok-serwis/tempsdb/issues
Classifier: Programming Language :: Python
Classifier: Programming Language :: Python :: 3.5
Classifier: Programming Language :: Python :: 3.6
Classifier: Programming Language :: Python :: 3.7
Classifier: Programming Language :: Python :: 3.8
Classifier: Programming Language :: Python :: 3.9
Classifier: Programming Language :: Python :: 3.10
Classifier: Programming Language :: Python :: 3.11
Classifier: Programming Language :: Python :: Implementation :: CPython
Classifier: Operating System :: POSIX
Classifier: Operating System :: OS Independent
Classifier: Development Status :: 5 - Production/Stable
Classifier: License :: OSI Approved :: MIT License
Classifier: Topic :: Software Development :: Libraries
Classifier: Topic :: Database
Requires-Python: !=2.7.*,!=3.0.*,!=3.1.*,!=3.2.*,!=3.3.*,!=3.4.*,!=3.5.*,!=3.6.*,!=3.7.*
License-File: LICENSE
Requires-Dist: satella >=2.17.7
Provides-Extra: fasterjson
Requires-Dist: ujson ; extra == 'fasterjson'
Provides-Extra: fastermetadata
Requires-Dist: minijson ; extra == 'fastermetadata'
